pyass/__init__.py
pyass/api/__init__.py
pyass/api/async_client.py
pyass/api/rest.py
pyass/assets/audio_refs.csv
pyass/assets/emojis.json
pyass/cli/__init__.py
pyass/cli/commands.py
pyass/cli/theme.py
pyass/core/__init__.py
pyass/core/cache.py
pyass/core/config.py
pyass/core/models.py
pyass/core/slangdb.py
pyass/data/__init__.py
pyass/data/base_slang.json
pyass/data/user_custom.json
pyass/engines/__init__.py
pyass/engines/mood_engine.py
pyass/engines/quizzer.py
pyass/engines/search.py
pyass/engines/translator.py
pyass/utils/__init__.py
pyass/utils/fuzzy.py
pyass/utils/metrics.py
pyass/utils/updater.py
pyass_genz-2025.1.0.dist-info/licenses/LICENSE
pyass_genz-2025.1.0.dist-info/METADATA
pyass_genz-2025.1.0.dist-info/WHEEL
pyass_genz-2025.1.0.dist-info/entry_points.txt
pyass_genz-2025.1.0.dist-info/top_level.txt
pyass_genz-2025.1.0.dist-info/RECORD
