Metadata-Version: 2.4
Name: pyass-genz
Version: 2025.1.0
Summary: The definitive Gen-Z & internet slang library for Python. Vibes > verbs.
Home-page: https://github.com/Zer0C0d3r/pyass-genz
Author: Zer0C0d3r
Author-email: Zer0C0d3r <odin.coder77@proton.me>
License: MIT
Project-URL: Homepage, https://github.com/Zer0C0d3r/pyass-genz
Project-URL: Repository, https://github.com/Zer0C0d3r/pyass-genz
Project-URL: Documentation, https://github.com/Zer0C0d3r/pyass-genz/blob/main/README.md
Keywords: slang,genz,tiktok,meme,internet,vibes,translator,quiz
Classifier: Development Status :: 5 - Production/Stable
Classifier: Intended Audience :: Developers
Classifier: Topic :: Sociology
Classifier: Topic :: Games/Entertainment
Classifier: Topic :: Software Development :: Libraries :: Python Modules
Classifier: License :: OSI Approved :: MIT License
Classifier: Programming Language :: Python :: 3
Classifier: Programming Language :: Python :: 3.9
Classifier: Programming Language :: Python :: 3.10
Classifier: Programming Language :: Python :: 3.11
Classifier: Programming Language :: Python :: 3.12
Classifier: Operating System :: OS Independent
Requires-Python: >=3.9
License-File: LICENSE
Requires-Dist: typer>=0.9.0
Requires-Dist: rich>=13.0.0
Requires-Dist: pydantic>=2.0.0
Requires-Dist: fastapi>=0.100.0
Requires-Dist: uvicorn>=0.23.0
Requires-Dist: aiohttp>=3.8.0
Requires-Dist: fuzzywuzzy>=0.18.0
Requires-Dist: python-levenshtein>=0.21.0; platform_system != "Windows"
Provides-Extra: ml
Requires-Dist: sentence-transformers>=2.2.0; extra == "ml"
Requires-Dist: scikit-learn>=1.2.0; extra == "ml"
Provides-Extra: dev
Requires-Dist: pytest>=7.0; extra == "dev"
Requires-Dist: pytest-asyncio>=0.21.0; extra == "dev"
Requires-Dist: black>=23.0; extra == "dev"
Requires-Dist: mypy>=1.4; extra == "dev"
Requires-Dist: httpx>=0.24.0; extra == "dev"
Dynamic: author
Dynamic: home-page
Dynamic: license-file
Dynamic: requires-python
